{
  "toptracks": {
    "track": [
      {
        "streamable": {
          "fulltrack": "0",
          "#text": "0"
        },
        "mbid": "696cdf53-d8cf-4973-9f8f-e5b73a6c0f09",
        "name": "Fix You",
        "image": [
          {
            "size": "small",
            "#text": "https://lastfm.freetls.fastly.net/i/u/34s/2a96cbd8b46e442fc41c2b86b821562f.png"
          },
          {
            "size": "medium",
            "#text": "https://lastfm.freetls.fastly.net/i/u/64s/2a96cbd8b46e442fc41c2b86b821562f.png"
          },
          {
            "size": "large",
            "#text": "https://lastfm.freetls.fastly.net/i/u/174s/2a96cbd8b46e442fc41c2b86b821562f.png"
          },
          {
            "size": "extralarge",
            "#text": "https://lastfm.freetls.fastly.net/i/u/300x300/2a96cbd8b46e442fc41c2b86b821562f.png"
          }
        ],
        "artist": {
          "url": "https://www.last.fm/music/Coldplay",
          "name": "Coldplay",
          "mbid": "cc197bad-dc9c-440d-a5b5-d52ba2e14234"
        },
        "url": "https://www.last.fm/music/Coldplay/_/Fix+You",
        "duration": "295",
        "@attr": {
          "rank": "1"
        },
        "playcount": "10"
      },
      {
        "streamable": {
          "fulltrack": "0",
          "#text": "0"
        },
        "mbid": "",
        "name": "Bajrang Baan-Lofi",
        "image": [
          {
            "size": "small",
            "#text": "https://lastfm.freetls.fastly.net/i/u/34s/2a96cbd8b46e442fc41c2b86b821562f.png"
          },
          {
            "size": "medium",
            "#text": "https://lastfm.freetls.fastly.net/i/u/64s/2a96cbd8b46e442fc41c2b86b821562f.png"
          },
          {
            "size": "large",
            "#text": "https://lastfm.freetls.fastly.net/i/u/174s/2a96cbd8b46e442fc41c2b86b821562f.png"
          },
          {
            "size": "extralarge",
            "#text": "https://lastfm.freetls.fastly.net/i/u/300x300/2a96cbd8b46e442fc41c2b86b821562f.png"
          }
        ],
        "artist": {
          "url": "https://www.last.fm/music/Rasraj+Ji+Maharaj",
          "name": "Rasraj Ji Maharaj",
          "mbid": ""
        },
        "url": "https://www.last.fm/music/Rasraj+Ji+Maharaj/_/Bajrang+Baan-Lofi",
        "duration": "217",
        "@attr": {
          "rank": "2"
        },
        "playcount": "6"
      },
      {
        "streamable": {
          "fulltrack": "0",
          "#text": "0"
        },
        "mbid": "3cfae970-1365-4b7c-aded-49d7b21dd9ce",
        "name": "Kashi Vishwanath Gange",
        "image": [
          {
            "size": "small",
            "#text": "https://lastfm.freetls.fastly.net/i/u/34s/2a96cbd8b46e442fc41c2b86b821562f.png"
          },
          {
            "size": "medium",
            "#text": "https://lastfm.freetls.fastly.net/i/u/64s/2a96cbd8b46e442fc41c2b86b821562f.png"
          },
          {
            "size": "large",
            "#text": "https://lastfm.freetls.fastly.net/i/u/174s/2a96cbd8b46e442fc41c2b86b821562f.png"
          },
          {
            "size": "extralarge",
            "#text": "https://lastfm.freetls.fastly.net/i/u/300x300/2a96cbd8b46e442fc41c2b86b821562f.png"
          }
        ],
        "artist": {
          "url": "https://www.last.fm/music/Krishna+Das",
          "name": "Krishna Das",
          "mbid": "9c0d337f-934c-45e9-a24e-c985b8059816"
        },
        "url": "https://www.last.fm/music/Krishna+Das/_/Kashi+Vishwanath+Gange",
        "duration": "389",
        "@attr": {
          "rank": "3"
        },
        "playcount": "5"
      },
      {
        "streamable": {
          "fulltrack": "0",
          "#text": "0"
        },
        "mbid": "db1803fb-0000-4ca7-8afb-9f0e21f4f144",
        "name": "squabble up",
        "image": [
          {
            "size": "small",
            "#text": "https://lastfm.freetls.fastly.net/i/u/34s/2a96cbd8b46e442fc41c2b86b821562f.png"
          },
          {
            "size": "medium",
            "#text": "https://lastfm.freetls.fastly.net/i/u/64s/2a96cbd8b46e442fc41c2b86b821562f.png"
          },
          {
            "size": "large",
            "#text": "https://lastfm.freetls.fastly.net/i/u/174s/2a96cbd8b46e442fc41c2b86b821562f.png"
          },
          {
            "size": "extralarge",
            "#text": "https://lastfm.freetls.fastly.net/i/u/300x300/2a96cbd8b46e442fc41c2b86b821562f.png"
          }
        ],
        "artist": {
          "url": "https://www.last.fm/music/Kendrick+Lamar",
          "name": "Kendrick Lamar",
          "mbid": "381086ea-f511-4aba-bdf9-71c753dc5077"
        },
        "url": "https://www.last.fm/music/Kendrick+Lamar/_/squabble+up",
        "duration": "157",
        "@attr": {
          "rank": "4"
        },
        "playcount": "4"
      },
      {
        "streamable": {
          "fulltrack": "0",
          "#text": "0"
        },
        "mbid": "7aac5a1a-a88f-475c-a9e3-91a5d8c2256c",
        "name": "euphoria",
        "image": [
          {
            "size": "small",
            "#text": "https://lastfm.freetls.fastly.net/i/u/34s/2a96cbd8b46e442fc41c2b86b821562f.png"
          },
          {
            "size": "medium",
            "#text": "https://lastfm.freetls.fastly.net/i/u/64s/2a96cbd8b46e442fc41c2b86b821562f.png"
          },
          {
            "size": "large",
            "#text": "https://lastfm.freetls.fastly.net/i/u/174s/2a96cbd8b46e442fc41c2b86b821562f.png"
          },
          {
            "size": "extralarge",
            "#text": "https://lastfm.freetls.fastly.net/i/u/300x300/2a96cbd8b46e442fc41c2b86b821562f.png"
          }
        ],
        "artist": {
          "url": "https://www.last.fm/music/Kendrick+Lamar",
          "name": "Kendrick Lamar",
          "mbid": "381086ea-f511-4aba-bdf9-71c753dc5077"
        },
        "url": "https://www.last.fm/music/Kendrick+Lamar/_/euphoria",
        "duration": "383",
        "@attr": {
          "rank": "5"
        },
        "playcount": "3"
      }
    ],
    "@attr": {
      "user": "KrishSkywalker",
      "totalPages": "11",
      "page": "1",
      "total": "54",
      "perPage": "5"
    }
  }
}